{
"issues":  [
{
"id":  "S1226",
"message":  "Introduce a new variable instead of reusing the parameter \"spanToFormat\".",
"location":  {
"uri":  "roslyn\\src\\EditorFeatures\\VisualBasic\\LineCommit\\CommitFormatter.vb",
"region":  {
"startLine":  39,
"startColumn":  17,
"endLine":  39,
"endColumn":  29
}
}
},
{
"id":  "S1226",
"message":  "Introduce a new variable instead of reusing the parameter \"dirtyRegion\".",
"location":  {
"uri":  "roslyn\\src\\EditorFeatures\\VisualBasic\\LineCommit\\CommitFormatter.vb",
"region":  {
"startLine":  40,
"startColumn":  17,
"endLine":  40,
"endColumn":  28
}
}
}
]
}
