{
"issues":  [
{
"id":  "S1144",
"message":  "Remove this unused private member.",
"location":  {
"uri":  "roslyn\\src\\Tools\\Source\\CompilerGeneratorTools\\Source\\BoundTreeGenerator\\BoundNodeClassWriter.cs",
"region":  {
"startLine":  724,
"startColumn":  9,
"endLine":  727,
"endColumn":  10
}
}
},
{
"id":  "S1144",
"message":  "Remove this unused private member.",
"location":  {
"uri":  "roslyn\\src\\Tools\\Source\\CompilerGeneratorTools\\Source\\BoundTreeGenerator\\BoundNodeClassWriter.cs",
"region":  {
"startLine":  1540,
"startColumn":  9,
"endLine":  1543,
"endColumn":  10
}
}
},
{
"id":  "S1144",
"message":  "Remove this unused private member.",
"location":  {
"uri":  "roslyn\\src\\Tools\\Source\\CompilerGeneratorTools\\Source\\BoundTreeGenerator\\BoundNodeClassWriter.cs",
"region":  {
"startLine":  1567,
"startColumn":  9,
"endLine":  1570,
"endColumn":  10
}
}
}
]
}
