{
"issues":  [
{
"id":  "S3254",
"message":  "Remove this default value assigned to parameter \"path\".",
"location":  {
"uri":  "roslyn\\src\\Compilers\\CSharp\\Test\\Syntax\\Diagnostics\\LocationsTests.cs",
"region":  {
"startLine":  184,
"startColumn":  80,
"endLine":  184,
"endColumn":  88
}
}
},
{
"id":  "S3254",
"message":  "Remove this default value assigned to parameter \"offset\".",
"location":  {
"uri":  "roslyn\\src\\Compilers\\CSharp\\Test\\Syntax\\Parsing\\DeconstructionTests.cs",
"region":  {
"startLine":  1545,
"startColumn":  64,
"endLine":  1545,
"endColumn":  73
}
}
},
{
"id":  "S3254",
"message":  "Remove this default value assigned to parameter \"offset\".",
"location":  {
"uri":  "roslyn\\src\\Compilers\\CSharp\\Test\\Syntax\\Parsing\\DeconstructionTests.cs",
"region":  {
"startLine":  1558,
"startColumn":  64,
"endLine":  1558,
"endColumn":  73
}
}
},
{
"id":  "S3254",
"message":  "Remove this default value assigned to parameter \"offset\".",
"location":  {
"uri":  "roslyn\\src\\Compilers\\CSharp\\Test\\Syntax\\Parsing\\DeconstructionTests.cs",
"region":  {
"startLine":  1570,
"startColumn":  64,
"endLine":  1570,
"endColumn":  73
}
}
},
{
"id":  "S3254",
"message":  "Remove this default value assigned to parameter \"offset\".",
"location":  {
"uri":  "roslyn\\src\\Compilers\\CSharp\\Test\\Syntax\\Parsing\\DeconstructionTests.cs",
"region":  {
"startLine":  1582,
"startColumn":  64,
"endLine":  1582,
"endColumn":  73
}
}
},
{
"id":  "S3254",
"message":  "Remove this default value assigned to parameter \"offset\".",
"location":  {
"uri":  "roslyn\\src\\Compilers\\CSharp\\Test\\Syntax\\Parsing\\DeconstructionTests.cs",
"region":  {
"startLine":  1594,
"startColumn":  64,
"endLine":  1594,
"endColumn":  73
}
}
},
{
"id":  "S3254",
"message":  "Remove this default value assigned to parameter \"offset\".",
"location":  {
"uri":  "roslyn\\src\\Compilers\\CSharp\\Test\\Syntax\\Parsing\\DeconstructionTests.cs",
"region":  {
"startLine":  1611,
"startColumn":  64,
"endLine":  1611,
"endColumn":  73
}
}
},
{
"id":  "S3254",
"message":  "Remove this default value assigned to parameter \"offset\".",
"location":  {
"uri":  "roslyn\\src\\Compilers\\CSharp\\Test\\Syntax\\Parsing\\DeconstructionTests.cs",
"region":  {
"startLine":  1628,
"startColumn":  64,
"endLine":  1628,
"endColumn":  73
}
}
},
{
"id":  "S3254",
"message":  "Remove this default value assigned to parameter \"offset\".",
"location":  {
"uri":  "roslyn\\src\\Compilers\\CSharp\\Test\\Syntax\\Parsing\\DeconstructionTests.cs",
"region":  {
"startLine":  1642,
"startColumn":  64,
"endLine":  1642,
"endColumn":  73
}
}
},
{
"id":  "S3254",
"message":  "Remove this default value assigned to parameter \"offset\".",
"location":  {
"uri":  "roslyn\\src\\Compilers\\CSharp\\Test\\Syntax\\Parsing\\DeconstructionTests.cs",
"region":  {
"startLine":  1656,
"startColumn":  64,
"endLine":  1656,
"endColumn":  73
}
}
},
{
"id":  "S3254",
"message":  "Remove this default value assigned to parameter \"offset\".",
"location":  {
"uri":  "roslyn\\src\\Compilers\\CSharp\\Test\\Syntax\\Parsing\\DeconstructionTests.cs",
"region":  {
"startLine":  1672,
"startColumn":  64,
"endLine":  1672,
"endColumn":  73
}
}
},
{
"id":  "S3254",
"message":  "Remove this default value assigned to parameter \"offset\".",
"location":  {
"uri":  "roslyn\\src\\Compilers\\CSharp\\Test\\Syntax\\Parsing\\DeconstructionTests.cs",
"region":  {
"startLine":  1683,
"startColumn":  64,
"endLine":  1683,
"endColumn":  73
}
}
},
{
"id":  "S3254",
"message":  "Remove this default value assigned to parameter \"offset\".",
"location":  {
"uri":  "roslyn\\src\\Compilers\\CSharp\\Test\\Syntax\\Parsing\\DeconstructionTests.cs",
"region":  {
"startLine":  1694,
"startColumn":  64,
"endLine":  1694,
"endColumn":  73
}
}
},
{
"id":  "S3254",
"message":  "Remove this default value assigned to parameter \"offset\".",
"location":  {
"uri":  "roslyn\\src\\Compilers\\CSharp\\Test\\Syntax\\Parsing\\DeconstructionTests.cs",
"region":  {
"startLine":  1703,
"startColumn":  64,
"endLine":  1703,
"endColumn":  73
}
}
},
{
"id":  "S3254",
"message":  "Remove this default value assigned to parameter \"offset\".",
"location":  {
"uri":  "roslyn\\src\\Compilers\\CSharp\\Test\\Syntax\\Parsing\\DeconstructionTests.cs",
"region":  {
"startLine":  1713,
"startColumn":  64,
"endLine":  1713,
"endColumn":  73
}
}
},
{
"id":  "S3254",
"message":  "Remove this default value assigned to parameter \"errorCount\".",
"location":  {
"uri":  "roslyn\\src\\Compilers\\CSharp\\Test\\Syntax\\Parsing\\RoundTrippingTests.cs",
"region":  {
"startLine":  91,
"startColumn":  69,
"endLine":  91,
"endColumn":  70
}
}
},
{
"id":  "S3254",
"message":  "Remove this default value assigned to parameter \"path\".",
"location":  {
"uri":  "roslyn\\src\\Compilers\\CSharp\\Test\\Syntax\\Parsing\\RoundTrippingTests.cs",
"region":  {
"startLine":  99,
"startColumn":  77,
"endLine":  99,
"endColumn":  85
}
}
},
{
"id":  "S3254",
"message":  "Remove this default value assigned to parameter \"errorCount\".",
"location":  {
"uri":  "roslyn\\src\\Compilers\\CSharp\\Test\\Syntax\\Parsing\\RoundTrippingTests.cs",
"region":  {
"startLine":  142,
"startColumn":  71,
"endLine":  142,
"endColumn":  72
}
}
},
{
"id":  "S3254",
"message":  "Remove this default value assigned to parameter \"errorCount\".",
"location":  {
"uri":  "roslyn\\src\\Compilers\\CSharp\\Test\\Syntax\\Parsing\\RoundTrippingTests.cs",
"region":  {
"startLine":  715,
"startColumn":  41,
"endLine":  715,
"endColumn":  42
}
}
},
{
"id":  "S3254",
"message":  "Remove this default value assigned to parameter \"errorCount\".",
"location":  {
"uri":  "roslyn\\src\\Compilers\\CSharp\\Test\\Syntax\\Parsing\\RoundTrippingTests.cs",
"region":  {
"startLine":  727,
"startColumn":  41,
"endLine":  727,
"endColumn":  42
}
}
},
{
"id":  "S3254",
"message":  "Remove this default value assigned to parameter \"path\".",
"location":  {
"uri":  "roslyn\\src\\Compilers\\CSharp\\Test\\Syntax\\Parsing\\RoundTrippingTests.cs",
"region":  {
"startLine":  1577,
"startColumn":  70,
"endLine":  1577,
"endColumn":  72
}
}
},
{
"id":  "S3254",
"message":  "Remove this default value assigned to parameter \"consumeFullText\".",
"location":  {
"uri":  "roslyn\\src\\Compilers\\CSharp\\Test\\Syntax\\Parsing\\RoundTrippingTests.cs",
"region":  {
"startLine":  1587,
"startColumn":  72,
"endLine":  1587,
"endColumn":  93
}
}
},
{
"id":  "S3254",
"message":  "Remove this default value assigned to parameter \"errorCount\".",
"location":  {
"uri":  "roslyn\\src\\Compilers\\CSharp\\Test\\Syntax\\Parsing\\RoundTrippingTests.cs",
"region":  {
"startLine":  1630,
"startColumn":  41,
"endLine":  1630,
"endColumn":  42
}
}
},
{
"id":  "S3254",
"message":  "Remove this default value assigned to parameter \"errorCount\".",
"location":  {
"uri":  "roslyn\\src\\Compilers\\CSharp\\Test\\Syntax\\Parsing\\RoundTrippingTests.cs",
"region":  {
"startLine":  1682,
"startColumn":  41,
"endLine":  1682,
"endColumn":  42
}
}
},
{
"id":  "S3254",
"message":  "Remove this default value assigned to parameter \"descendIntoTrivia\".",
"location":  {
"uri":  "roslyn\\src\\Compilers\\CSharp\\Test\\Syntax\\Parsing\\StatementParsingTests.cs",
"region":  {
"startLine":  2535,
"startColumn":  49,
"endLine":  2535,
"endColumn":  73
}
}
},
{
"id":  "S3254",
"message":  "Remove this default value assigned to parameter \"encoding\".",
"location":  {
"uri":  "roslyn\\src\\Compilers\\CSharp\\Test\\Syntax\\Syntax\\SyntaxFactoryTests.cs",
"region":  {
"startLine":  20,
"startColumn":  82,
"endLine":  20,
"endColumn":  96
}
}
},
{
"id":  "S3254",
"message":  "Remove this default value assigned to parameter \"findInsideTrivia\".",
"location":  {
"uri":  "roslyn\\src\\Compilers\\CSharp\\Test\\Syntax\\Syntax\\SyntaxNodeTests.cs",
"region":  {
"startLine":  531,
"startColumn":  57,
"endLine":  531,
"endColumn":  80
}
}
},
{
"id":  "S3254",
"message":  "Remove this default value assigned to parameter \"findInsideTrivia\".",
"location":  {
"uri":  "roslyn\\src\\Compilers\\CSharp\\Test\\Syntax\\Syntax\\SyntaxNodeTests.cs",
"region":  {
"startLine":  540,
"startColumn":  68,
"endLine":  540,
"endColumn":  91
}
}
},
{
"id":  "S3254",
"message":  "Remove this default value assigned to parameter \"findInsideTrivia\".",
"location":  {
"uri":  "roslyn\\src\\Compilers\\CSharp\\Test\\Syntax\\Syntax\\SyntaxNodeTests.cs",
"region":  {
"startLine":  544,
"startColumn":  78,
"endLine":  544,
"endColumn":  101
}
}
},
{
"id":  "S3254",
"message":  "Remove this default value assigned to parameter \"findInsideTrivia\".",
"location":  {
"uri":  "roslyn\\src\\Compilers\\CSharp\\Test\\Syntax\\Syntax\\SyntaxNodeTests.cs",
"region":  {
"startLine":  548,
"startColumn":  55,
"endLine":  548,
"endColumn":  78
}
}
},
{
"id":  "S3254",
"message":  "Remove this default value assigned to parameter \"findInsideTrivia\".",
"location":  {
"uri":  "roslyn\\src\\Compilers\\CSharp\\Test\\Syntax\\Syntax\\SyntaxNodeTests.cs",
"region":  {
"startLine":  558,
"startColumn":  73,
"endLine":  558,
"endColumn":  96
}
}
},
{
"id":  "S3254",
"message":  "Remove this default value assigned to parameter \"findInsideTrivia\".",
"location":  {
"uri":  "roslyn\\src\\Compilers\\CSharp\\Test\\Syntax\\Syntax\\SyntaxNodeTests.cs",
"region":  {
"startLine":  560,
"startColumn":  79,
"endLine":  560,
"endColumn":  102
}
}
},
{
"id":  "S3254",
"message":  "Remove this default value assigned to parameter \"includeSkipped\".",
"location":  {
"uri":  "roslyn\\src\\Compilers\\CSharp\\Test\\Syntax\\Syntax\\SyntaxNodeTests.cs",
"region":  {
"startLine":  801,
"startColumn":  69,
"endLine":  801,
"endColumn":  90
}
}
},
{
"id":  "S3254",
"message":  "Remove this default value assigned to parameter \"includeSkipped\".",
"location":  {
"uri":  "roslyn\\src\\Compilers\\CSharp\\Test\\Syntax\\Syntax\\SyntaxNodeTests.cs",
"region":  {
"startLine":  805,
"startColumn":  44,
"endLine":  805,
"endColumn":  65
}
}
},
{
"id":  "S3254",
"message":  "Remove this default value assigned to parameter \"includeSkipped\".",
"location":  {
"uri":  "roslyn\\src\\Compilers\\CSharp\\Test\\Syntax\\Syntax\\SyntaxNodeTests.cs",
"region":  {
"startLine":  905,
"startColumn":  68,
"endLine":  905,
"endColumn":  89
}
}
},
{
"id":  "S3254",
"message":  "Remove this default value assigned to parameter \"includeSkipped\".",
"location":  {
"uri":  "roslyn\\src\\Compilers\\CSharp\\Test\\Syntax\\Syntax\\SyntaxNodeTests.cs",
"region":  {
"startLine":  909,
"startColumn":  48,
"endLine":  909,
"endColumn":  69
}
}
},
{
"id":  "S3254",
"message":  "Remove this default value assigned to parameter \"includeZeroWidth\".",
"location":  {
"uri":  "roslyn\\src\\Compilers\\CSharp\\Test\\Syntax\\Syntax\\SyntaxNodeTests.cs",
"region":  {
"startLine":  928,
"startColumn":  59,
"endLine":  928,
"endColumn":  82
}
}
},
{
"id":  "S3254",
"message":  "Remove this default value assigned to parameter \"indentation\".",
"location":  {
"uri":  "roslyn\\src\\Compilers\\CSharp\\Test\\Syntax\\Syntax\\SyntaxNormalizerTests.cs",
"region":  {
"startLine":  509,
"startColumn":  53,
"endLine":  509,
"endColumn":  59
}
}
}
]
}
