{
"issues":  [
{
"id":  "S104",
"message":  "This file has 7347 lines, which is greater than 1000 authorized. Split it into smaller files.",
"location":  {
"uri":  "roslyn\\src\\Compilers\\CSharp\\Test\\Emit\\Attributes\\AttributeTests.cs",
"region":  {
"startLine":  1,
"startColumn":  1,
"endLine":  1,
"endColumn":  161
}
}
},
{
"id":  "S104",
"message":  "This file has 2072 lines, which is greater than 1000 authorized. Split it into smaller files.",
"location":  {
"uri":  "roslyn\\src\\Compilers\\CSharp\\Test\\Emit\\Attributes\\AttributeTests_Assembly.cs",
"region":  {
"startLine":  1,
"startColumn":  1,
"endLine":  1,
"endColumn":  161
}
}
},
{
"id":  "S104",
"message":  "This file has 2955 lines, which is greater than 1000 authorized. Split it into smaller files.",
"location":  {
"uri":  "roslyn\\src\\Compilers\\CSharp\\Test\\Emit\\Attributes\\AttributeTests_CallerInfoAttributes.cs",
"region":  {
"startLine":  1,
"startColumn":  1,
"endLine":  1,
"endColumn":  161
}
}
},
{
"id":  "S104",
"message":  "This file has 1386 lines, which is greater than 1000 authorized. Split it into smaller files.",
"location":  {
"uri":  "roslyn\\src\\Compilers\\CSharp\\Test\\Emit\\Attributes\\AttributeTests_Dynamic.cs",
"region":  {
"startLine":  1,
"startColumn":  1,
"endLine":  1,
"endColumn":  161
}
}
},
{
"id":  "S104",
"message":  "This file has 1166 lines, which is greater than 1000 authorized. Split it into smaller files.",
"location":  {
"uri":  "roslyn\\src\\Compilers\\CSharp\\Test\\Emit\\Attributes\\AttributeTests_Locations.cs",
"region":  {
"startLine":  1,
"startColumn":  1,
"endLine":  1,
"endColumn":  161
}
}
},
{
"id":  "S104",
"message":  "This file has 1359 lines, which is greater than 1000 authorized. Split it into smaller files.",
"location":  {
"uri":  "roslyn\\src\\Compilers\\CSharp\\Test\\Emit\\Attributes\\AttributeTests_MarshalAs.cs",
"region":  {
"startLine":  1,
"startColumn":  1,
"endLine":  1,
"endColumn":  161
}
}
},
{
"id":  "S104",
"message":  "This file has 1566 lines, which is greater than 1000 authorized. Split it into smaller files.",
"location":  {
"uri":  "roslyn\\src\\Compilers\\CSharp\\Test\\Emit\\Attributes\\AttributeTests_Security.cs",
"region":  {
"startLine":  1,
"startColumn":  1,
"endLine":  1,
"endColumn":  161
}
}
},
{
"id":  "S104",
"message":  "This file has 8411 lines, which is greater than 1000 authorized. Split it into smaller files.",
"location":  {
"uri":  "roslyn\\src\\Compilers\\CSharp\\Test\\Emit\\Attributes\\AttributeTests_WellKnownAttributes.cs",
"region":  {
"startLine":  1,
"startColumn":  1,
"endLine":  1,
"endColumn":  161
}
}
},
{
"id":  "S104",
"message":  "This file has 2190 lines, which is greater than 1000 authorized. Split it into smaller files.",
"location":  {
"uri":  "roslyn\\src\\Compilers\\CSharp\\Test\\Emit\\Attributes\\InternalsVisibleToAndStrongNameTests.cs",
"region":  {
"startLine":  1,
"startColumn":  1,
"endLine":  1,
"endColumn":  161
}
}
},
{
"id":  "S104",
"message":  "This file has 1624 lines, which is greater than 1000 authorized. Split it into smaller files.",
"location":  {
"uri":  "roslyn\\src\\Compilers\\CSharp\\Test\\Emit\\BreakingChanges.cs",
"region":  {
"startLine":  1,
"startColumn":  1,
"endLine":  1,
"endColumn":  161
}
}
},
{
"id":  "S104",
"message":  "This file has 1687 lines, which is greater than 1000 authorized. Split it into smaller files.",
"location":  {
"uri":  "roslyn\\src\\Compilers\\CSharp\\Test\\Emit\\CodeGen\\CodeGenAsyncEHTests.cs",
"region":  {
"startLine":  1,
"startColumn":  1,
"endLine":  1,
"endColumn":  161
}
}
},
{
"id":  "S104",
"message":  "This file has 2939 lines, which is greater than 1000 authorized. Split it into smaller files.",
"location":  {
"uri":  "roslyn\\src\\Compilers\\CSharp\\Test\\Emit\\CodeGen\\CodeGenAsyncSpillTests.cs",
"region":  {
"startLine":  1,
"startColumn":  1,
"endLine":  1,
"endColumn":  161
}
}
},
{
"id":  "S104",
"message":  "This file has 4395 lines, which is greater than 1000 authorized. Split it into smaller files.",
"location":  {
"uri":  "roslyn\\src\\Compilers\\CSharp\\Test\\Emit\\CodeGen\\CodeGenAsyncTests.cs",
"region":  {
"startLine":  1,
"startColumn":  1,
"endLine":  1,
"endColumn":  161
}
}
},
{
"id":  "S104",
"message":  "This file has 2372 lines, which is greater than 1000 authorized. Split it into smaller files.",
"location":  {
"uri":  "roslyn\\src\\Compilers\\CSharp\\Test\\Emit\\CodeGen\\CodeGenCheckedTests.cs",
"region":  {
"startLine":  1,
"startColumn":  1,
"endLine":  1,
"endColumn":  161
}
}
},
{
"id":  "S104",
"message":  "This file has 5297 lines, which is greater than 1000 authorized. Split it into smaller files.",
"location":  {
"uri":  "roslyn\\src\\Compilers\\CSharp\\Test\\Emit\\CodeGen\\CodeGenClosureLambdaTests.cs",
"region":  {
"startLine":  1,
"startColumn":  1,
"endLine":  1,
"endColumn":  161
}
}
},
{
"id":  "S104",
"message":  "This file has 2331 lines, which is greater than 1000 authorized. Split it into smaller files.",
"location":  {
"uri":  "roslyn\\src\\Compilers\\CSharp\\Test\\Emit\\CodeGen\\CodeGenConditionalOperatorTests.cs",
"region":  {
"startLine":  1,
"startColumn":  1,
"endLine":  1,
"endColumn":  161
}
}
},
{
"id":  "S104",
"message":  "This file has 1073 lines, which is greater than 1000 authorized. Split it into smaller files.",
"location":  {
"uri":  "roslyn\\src\\Compilers\\CSharp\\Test\\Emit\\CodeGen\\CodeGenConversionTests.cs",
"region":  {
"startLine":  1,
"startColumn":  1,
"endLine":  1,
"endColumn":  161
}
}
},
{
"id":  "S104",
"message":  "This file has 3049 lines, which is greater than 1000 authorized. Split it into smaller files.",
"location":  {
"uri":  "roslyn\\src\\Compilers\\CSharp\\Test\\Emit\\CodeGen\\CodeGenDeconstructTests.cs",
"region":  {
"startLine":  1,
"startColumn":  1,
"endLine":  1,
"endColumn":  161
}
}
},
{
"id":  "S104",
"message":  "This file has 1076 lines, which is greater than 1000 authorized. Split it into smaller files.",
"location":  {
"uri":  "roslyn\\src\\Compilers\\CSharp\\Test\\Emit\\CodeGen\\CodeGenExplicitImplementationTests.cs",
"region":  {
"startLine":  1,
"startColumn":  1,
"endLine":  1,
"endColumn":  161
}
}
},
{
"id":  "S104",
"message":  "This file has 6587 lines, which is greater than 1000 authorized. Split it into smaller files.",
"location":  {
"uri":  "roslyn\\src\\Compilers\\CSharp\\Test\\Emit\\CodeGen\\CodeGenExprLambdaTests.cs",
"region":  {
"startLine":  1,
"startColumn":  1,
"endLine":  1,
"endColumn":  161
}
}
},
{
"id":  "S104",
"message":  "This file has 1995 lines, which is greater than 1000 authorized. Split it into smaller files.",
"location":  {
"uri":  "roslyn\\src\\Compilers\\CSharp\\Test\\Emit\\CodeGen\\CodeGenForEachTests.cs",
"region":  {
"startLine":  1,
"startColumn":  1,
"endLine":  1,
"endColumn":  161
}
}
},
{
"id":  "S104",
"message":  "This file has 2300 lines, which is greater than 1000 authorized. Split it into smaller files.",
"location":  {
"uri":  "roslyn\\src\\Compilers\\CSharp\\Test\\Emit\\CodeGen\\CodeGenImplicitImplementationTests.cs",
"region":  {
"startLine":  1,
"startColumn":  1,
"endLine":  1,
"endColumn":  161
}
}
},
{
"id":  "S104",
"message":  "This file has 1023 lines, which is greater than 1000 authorized. Split it into smaller files.",
"location":  {
"uri":  "roslyn\\src\\Compilers\\CSharp\\Test\\Emit\\CodeGen\\CodeGenImplicitlyTypeArraysTests.cs",
"region":  {
"startLine":  1,
"startColumn":  1,
"endLine":  1,
"endColumn":  161
}
}
},
{
"id":  "S104",
"message":  "This file has 1076 lines, which is greater than 1000 authorized. Split it into smaller files.",
"location":  {
"uri":  "roslyn\\src\\Compilers\\CSharp\\Test\\Emit\\CodeGen\\CodeGenIncrementTests.cs",
"region":  {
"startLine":  1,
"startColumn":  1,
"endLine":  1,
"endColumn":  161
}
}
},
{
"id":  "S104",
"message":  "This file has 2769 lines, which is greater than 1000 authorized. Split it into smaller files.",
"location":  {
"uri":  "roslyn\\src\\Compilers\\CSharp\\Test\\Emit\\CodeGen\\CodeGenInterfaceImplementation.cs",
"region":  {
"startLine":  1,
"startColumn":  1,
"endLine":  1,
"endColumn":  161
}
}
},
{
"id":  "S104",
"message":  "This file has 2679 lines, which is greater than 1000 authorized. Split it into smaller files.",
"location":  {
"uri":  "roslyn\\src\\Compilers\\CSharp\\Test\\Emit\\CodeGen\\CodeGenLocalFunctionTests.cs",
"region":  {
"startLine":  1,
"startColumn":  1,
"endLine":  1,
"endColumn":  45
}
}
},
{
"id":  "S104",
"message":  "This file has 2052 lines, which is greater than 1000 authorized. Split it into smaller files.",
"location":  {
"uri":  "roslyn\\src\\Compilers\\CSharp\\Test\\Emit\\CodeGen\\CodeGenLockTests.cs",
"region":  {
"startLine":  1,
"startColumn":  1,
"endLine":  1,
"endColumn":  161
}
}
},
{
"id":  "S104",
"message":  "This file has 4985 lines, which is greater than 1000 authorized. Split it into smaller files.",
"location":  {
"uri":  "roslyn\\src\\Compilers\\CSharp\\Test\\Emit\\CodeGen\\CodeGenOperators.cs",
"region":  {
"startLine":  1,
"startColumn":  1,
"endLine":  1,
"endColumn":  161
}
}
},
{
"id":  "S104",
"message":  "This file has 2425 lines, which is greater than 1000 authorized. Split it into smaller files.",
"location":  {
"uri":  "roslyn\\src\\Compilers\\CSharp\\Test\\Emit\\CodeGen\\CodeGenOptimizedNullableOperators.cs",
"region":  {
"startLine":  1,
"startColumn":  1,
"endLine":  1,
"endColumn":  161
}
}
},
{
"id":  "S104",
"message":  "This file has 4313 lines, which is greater than 1000 authorized. Split it into smaller files.",
"location":  {
"uri":  "roslyn\\src\\Compilers\\CSharp\\Test\\Emit\\CodeGen\\CodeGenOverridingAndHiding.cs",
"region":  {
"startLine":  1,
"startColumn":  1,
"endLine":  1,
"endColumn":  161
}
}
},
{
"id":  "S104",
"message":  "This file has 1605 lines, which is greater than 1000 authorized. Split it into smaller files.",
"location":  {
"uri":  "roslyn\\src\\Compilers\\CSharp\\Test\\Emit\\CodeGen\\CodeGenRefLocalTests.cs",
"region":  {
"startLine":  1,
"startColumn":  1,
"endLine":  1,
"endColumn":  184
}
}
},
{
"id":  "S104",
"message":  "This file has 2429 lines, which is greater than 1000 authorized. Split it into smaller files.",
"location":  {
"uri":  "roslyn\\src\\Compilers\\CSharp\\Test\\Emit\\CodeGen\\CodeGenRefReturnTests.cs",
"region":  {
"startLine":  1,
"startColumn":  1,
"endLine":  1,
"endColumn":  184
}
}
},
{
"id":  "S104",
"message":  "This file has 6897 lines, which is greater than 1000 authorized. Split it into smaller files.",
"location":  {
"uri":  "roslyn\\src\\Compilers\\CSharp\\Test\\Emit\\CodeGen\\CodeGenShortCircuitOperatorTests.cs",
"region":  {
"startLine":  1,
"startColumn":  1,
"endLine":  1,
"endColumn":  161
}
}
},
{
"id":  "S104",
"message":  "This file has 1077 lines, which is greater than 1000 authorized. Split it into smaller files.",
"location":  {
"uri":  "roslyn\\src\\Compilers\\CSharp\\Test\\Emit\\CodeGen\\CodeGenStringConcat.cs",
"region":  {
"startLine":  1,
"startColumn":  1,
"endLine":  1,
"endColumn":  161
}
}
},
{
"id":  "S104",
"message":  "This file has 1842 lines, which is greater than 1000 authorized. Split it into smaller files.",
"location":  {
"uri":  "roslyn\\src\\Compilers\\CSharp\\Test\\Emit\\CodeGen\\CodeGenStructsAndEnum.cs",
"region":  {
"startLine":  1,
"startColumn":  1,
"endLine":  1,
"endColumn":  161
}
}
},
{
"id":  "S104",
"message":  "This file has 15309 lines, which is greater than 1000 authorized. Split it into smaller files.",
"location":  {
"uri":  "roslyn\\src\\Compilers\\CSharp\\Test\\Emit\\CodeGen\\CodeGenTests.cs",
"region":  {
"startLine":  1,
"startColumn":  1,
"endLine":  1,
"endColumn":  161
}
}
},
{
"id":  "S104",
"message":  "This file has 3312 lines, which is greater than 1000 authorized. Split it into smaller files.",
"location":  {
"uri":  "roslyn\\src\\Compilers\\CSharp\\Test\\Emit\\CodeGen\\CodeGenTryFinally.cs",
"region":  {
"startLine":  1,
"startColumn":  1,
"endLine":  1,
"endColumn":  161
}
}
},
{
"id":  "S104",
"message":  "This file has 17813 lines, which is greater than 1000 authorized. Split it into smaller files.",
"location":  {
"uri":  "roslyn\\src\\Compilers\\CSharp\\Test\\Emit\\CodeGen\\CodeGenTupleTest.cs",
"region":  {
"startLine":  1,
"startColumn":  1,
"endLine":  1,
"endColumn":  161
}
}
},
{
"id":  "S104",
"message":  "This file has 2852 lines, which is greater than 1000 authorized. Split it into smaller files.",
"location":  {
"uri":  "roslyn\\src\\Compilers\\CSharp\\Test\\Emit\\CodeGen\\CodeGenUsingStatementTests.cs",
"region":  {
"startLine":  1,
"startColumn":  1,
"endLine":  1,
"endColumn":  161
}
}
},
{
"id":  "S104",
"message":  "This file has 1050 lines, which is greater than 1000 authorized. Split it into smaller files.",
"location":  {
"uri":  "roslyn\\src\\Compilers\\CSharp\\Test\\Emit\\CodeGen\\ForeachTest.cs",
"region":  {
"startLine":  1,
"startColumn":  1,
"endLine":  1,
"endColumn":  161
}
}
},
{
"id":  "S104",
"message":  "This file has 1933 lines, which is greater than 1000 authorized. Split it into smaller files.",
"location":  {
"uri":  "roslyn\\src\\Compilers\\CSharp\\Test\\Emit\\CodeGen\\ForLoopsTests.cs",
"region":  {
"startLine":  1,
"startColumn":  1,
"endLine":  1,
"endColumn":  161
}
}
},
{
"id":  "S104",
"message":  "This file has 1121 lines, which is greater than 1000 authorized. Split it into smaller files.",
"location":  {
"uri":  "roslyn\\src\\Compilers\\CSharp\\Test\\Emit\\CodeGen\\GotoTest.cs",
"region":  {
"startLine":  1,
"startColumn":  1,
"endLine":  1,
"endColumn":  161
}
}
},
{
"id":  "S104",
"message":  "This file has 1134 lines, which is greater than 1000 authorized. Split it into smaller files.",
"location":  {
"uri":  "roslyn\\src\\Compilers\\CSharp\\Test\\Emit\\CodeGen\\IndexerTests.cs",
"region":  {
"startLine":  1,
"startColumn":  1,
"endLine":  1,
"endColumn":  161
}
}
},
{
"id":  "S104",
"message":  "This file has 3415 lines, which is greater than 1000 authorized. Split it into smaller files.",
"location":  {
"uri":  "roslyn\\src\\Compilers\\CSharp\\Test\\Emit\\CodeGen\\ObjectAndCollectionInitializerTests.cs",
"region":  {
"startLine":  1,
"startColumn":  1,
"endLine":  1,
"endColumn":  161
}
}
},
{
"id":  "S104",
"message":  "This file has 6957 lines, which is greater than 1000 authorized. Split it into smaller files.",
"location":  {
"uri":  "roslyn\\src\\Compilers\\CSharp\\Test\\Emit\\CodeGen\\SwitchTests.cs",
"region":  {
"startLine":  1,
"startColumn":  1,
"endLine":  1,
"endColumn":  161
}
}
},
{
"id":  "S104",
"message":  "This file has 9223 lines, which is greater than 1000 authorized. Split it into smaller files.",
"location":  {
"uri":  "roslyn\\src\\Compilers\\CSharp\\Test\\Emit\\CodeGen\\UnsafeTests.cs",
"region":  {
"startLine":  1,
"startColumn":  1,
"endLine":  1,
"endColumn":  161
}
}
},
{
"id":  "S104",
"message":  "This file has 3002 lines, which is greater than 1000 authorized. Split it into smaller files.",
"location":  {
"uri":  "roslyn\\src\\Compilers\\CSharp\\Test\\Emit\\Emit\\CompilationEmitTests.cs",
"region":  {
"startLine":  1,
"startColumn":  1,
"endLine":  1,
"endColumn":  161
}
}
},
{
"id":  "S104",
"message":  "This file has 1964 lines, which is greater than 1000 authorized. Split it into smaller files.",
"location":  {
"uri":  "roslyn\\src\\Compilers\\CSharp\\Test\\Emit\\Emit\\DynamicAnalysis\\DynamicInstrumentationTests.cs",
"region":  {
"startLine":  1,
"startColumn":  1,
"endLine":  1,
"endColumn":  161
}
}
},
{
"id":  "S104",
"message":  "This file has 3035 lines, which is greater than 1000 authorized. Split it into smaller files.",
"location":  {
"uri":  "roslyn\\src\\Compilers\\CSharp\\Test\\Emit\\Emit\\EditAndContinue\\EditAndContinueClosureTests.cs",
"region":  {
"startLine":  1,
"startColumn":  1,
"endLine":  1,
"endColumn":  161
}
}
},
{
"id":  "S104",
"message":  "This file has 5411 lines, which is greater than 1000 authorized. Split it into smaller files.",
"location":  {
"uri":  "roslyn\\src\\Compilers\\CSharp\\Test\\Emit\\Emit\\EditAndContinue\\EditAndContinueStateMachineTests.cs",
"region":  {
"startLine":  1,
"startColumn":  1,
"endLine":  1,
"endColumn":  161
}
}
},
{
"id":  "S104",
"message":  "This file has 7188 lines, which is greater than 1000 authorized. Split it into smaller files.",
"location":  {
"uri":  "roslyn\\src\\Compilers\\CSharp\\Test\\Emit\\Emit\\EditAndContinue\\EditAndContinueTests.cs",
"region":  {
"startLine":  1,
"startColumn":  1,
"endLine":  1,
"endColumn":  161
}
}
},
{
"id":  "S104",
"message":  "This file has 3023 lines, which is greater than 1000 authorized. Split it into smaller files.",
"location":  {
"uri":  "roslyn\\src\\Compilers\\CSharp\\Test\\Emit\\Emit\\EditAndContinue\\LocalSlotMappingTests.cs",
"region":  {
"startLine":  1,
"startColumn":  1,
"endLine":  1,
"endColumn":  161
}
}
},
{
"id":  "S104",
"message":  "This file has 2490 lines, which is greater than 1000 authorized. Split it into smaller files.",
"location":  {
"uri":  "roslyn\\src\\Compilers\\CSharp\\Test\\Emit\\Emit\\EmitMetadata.cs",
"region":  {
"startLine":  1,
"startColumn":  1,
"endLine":  1,
"endColumn":  161
}
}
},
{
"id":  "S104",
"message":  "This file has 1449 lines, which is greater than 1000 authorized. Split it into smaller files.",
"location":  {
"uri":  "roslyn\\src\\Compilers\\CSharp\\Test\\Emit\\Emit\\EntryPointTests.cs",
"region":  {
"startLine":  1,
"startColumn":  1,
"endLine":  1,
"endColumn":  161
}
}
},
{
"id":  "S104",
"message":  "This file has 5848 lines, which is greater than 1000 authorized. Split it into smaller files.",
"location":  {
"uri":  "roslyn\\src\\Compilers\\CSharp\\Test\\Emit\\Emit\\NoPiaEmbedTypes.cs",
"region":  {
"startLine":  1,
"startColumn":  1,
"endLine":  1,
"endColumn":  161
}
}
},
{
"id":  "S104",
"message":  "This file has 1704 lines, which is greater than 1000 authorized. Split it into smaller files.",
"location":  {
"uri":  "roslyn\\src\\Compilers\\CSharp\\Test\\Emit\\PDB\\PDBAsyncTests.cs",
"region":  {
"startLine":  1,
"startColumn":  1,
"endLine":  1,
"endColumn":  161
}
}
},
{
"id":  "S104",
"message":  "This file has 2105 lines, which is greater than 1000 authorized. Split it into smaller files.",
"location":  {
"uri":  "roslyn\\src\\Compilers\\CSharp\\Test\\Emit\\PDB\\PDBDynamicLocalsTests.cs",
"region":  {
"startLine":  1,
"startColumn":  1,
"endLine":  1,
"endColumn":  161
}
}
},
{
"id":  "S104",
"message":  "This file has 1484 lines, which is greater than 1000 authorized. Split it into smaller files.",
"location":  {
"uri":  "roslyn\\src\\Compilers\\CSharp\\Test\\Emit\\PDB\\PDBIteratorTests.cs",
"region":  {
"startLine":  1,
"startColumn":  1,
"endLine":  1,
"endColumn":  161
}
}
},
{
"id":  "S104",
"message":  "This file has 1420 lines, which is greater than 1000 authorized. Split it into smaller files.",
"location":  {
"uri":  "roslyn\\src\\Compilers\\CSharp\\Test\\Emit\\PDB\\PDBLambdaTests.cs",
"region":  {
"startLine":  1,
"startColumn":  1,
"endLine":  1,
"endColumn":  161
}
}
},
{
"id":  "S104",
"message":  "This file has 5380 lines, which is greater than 1000 authorized. Split it into smaller files.",
"location":  {
"uri":  "roslyn\\src\\Compilers\\CSharp\\Test\\Emit\\PDB\\PDBTests.cs",
"region":  {
"startLine":  1,
"startColumn":  1,
"endLine":  1,
"endColumn":  161
}
}
},
{
"id":  "S104",
"message":  "This file has 2478 lines, which is greater than 1000 authorized. Split it into smaller files.",
"location":  {
"uri":  "roslyn\\src\\Compilers\\CSharp\\Test\\Emit\\PDB\\PDBUsingTests.cs",
"region":  {
"startLine":  1,
"startColumn":  1,
"endLine":  1,
"endColumn":  161
}
}
}
]
}
