{
"issues":  [
{
"id":  "S2259",
"message":  "\"invalidChars\" is null on at least one execution path.",
"location":  {
"uri":  "roslyn\\src\\EditorFeatures\\Test\\Completion\\AbstractCompletionProviderTests.cs",
"region":  {
"startLine":  799,
"startColumn":  36,
"endLine":  799,
"endColumn":  48
}
}
},
{
"id":  "S2259",
"message":  "\"trackingService\" is null on at least one execution path.",
"location":  {
"uri":  "roslyn\\src\\EditorFeatures\\Test\\EditAndContinue\\EditAndContinueTestHelpers.cs",
"region":  {
"startLine":  162,
"startColumn":  32,
"endLine":  162,
"endColumn":  47
}
}
},
{
"id":  "S2259",
"message":  "\"metadataSources\" is null on at least one execution path.",
"location":  {
"uri":  "roslyn\\src\\EditorFeatures\\Test\\MetadataAsSource\\AbstractMetadataAsSourceTests.TestContext.cs",
"region":  {
"startLine":  226,
"startColumn":  40,
"endLine":  226,
"endColumn":  55
}
}
},
{
"id":  "S2259",
"message":  "\"parseOptions\" is null on at least one execution path.",
"location":  {
"uri":  "roslyn\\src\\EditorFeatures\\Test\\Workspaces\\TestWorkspace_Create.cs",
"region":  {
"startLine":  162,
"startColumn":  33,
"endLine":  162,
"endColumn":  45
}
}
},
{
"id":  "S2259",
"message":  "\"parseOptions\" is null on at least one execution path.",
"location":  {
"uri":  "roslyn\\src\\EditorFeatures\\Test\\Workspaces\\TestWorkspace_Create.cs",
"region":  {
"startLine":  168,
"startColumn":  33,
"endLine":  168,
"endColumn":  45
}
}
}
]
}
