{
"issues":  [
{
"id":  "S108",
"message":  "Either remove or fill this block of code.",
"location":  {
"uri":  "roslyn\\src\\EditorFeatures\\Test\\Collections\\IntervalTreeTests.cs",
"region":  {
"startLine":  252,
"startColumn":  13,
"endLine":  253,
"endColumn":  14
}
}
},
{
"id":  "S108",
"message":  "Either remove or fill this block of code.",
"location":  {
"uri":  "roslyn\\src\\EditorFeatures\\Test\\Utilities\\TestWaitContext.cs",
"region":  {
"startLine":  53,
"startColumn":  13,
"endLine":  54,
"endColumn":  14
}
}
},
{
"id":  "S108",
"message":  "Either remove or fill this block of code.",
"location":  {
"uri":  "roslyn\\src\\EditorFeatures\\Test\\Utilities\\TestWaitContext.cs",
"region":  {
"startLine":  65,
"startColumn":  13,
"endLine":  66,
"endColumn":  14
}
}
},
{
"id":  "S108",
"message":  "Either remove or fill this block of code.",
"location":  {
"uri":  "roslyn\\src\\EditorFeatures\\Test\\Utilities\\TestWaitIndicator.cs",
"region":  {
"startLine":  90,
"startColumn":  17,
"endLine":  91,
"endColumn":  18
}
}
},
{
"id":  "S108",
"message":  "Either remove or fill this block of code.",
"location":  {
"uri":  "roslyn\\src\\EditorFeatures\\Test\\Utilities\\TestWaitIndicator.cs",
"region":  {
"startLine":  102,
"startColumn":  17,
"endLine":  103,
"endColumn":  18
}
}
},
{
"id":  "S108",
"message":  "Either remove or fill this block of code.",
"location":  {
"uri":  "roslyn\\src\\EditorFeatures\\Test\\Workspaces\\TestHostProject.cs",
"region":  {
"startLine":  362,
"startColumn":  13,
"endLine":  363,
"endColumn":  14
}
}
}
]
}
