{
"issues":  [
{
"id":  "S2971",
"message":  "Drop \"Where\" and move the condition into the \"Count\".",
"location":  {
"uri":  "roslyn\\src\\InteractiveWindow\\EditorTest\\InteractiveWindowTests.cs",
"region":  {
"startLine":  184,
"startColumn":  38,
"endLine":  184,
"endColumn":  43
}
}
},
{
"id":  "S2971",
"message":  "Drop \"Where\" and move the condition into the \"Count\".",
"location":  {
"uri":  "roslyn\\src\\InteractiveWindow\\EditorTest\\InteractiveWindowTests.cs",
"region":  {
"startLine":  185,
"startColumn":  38,
"endLine":  185,
"endColumn":  43
}
}
},
{
"id":  "S2971",
"message":  "Drop \"Where\" and move the condition into the \"SingleOrDefault\".",
"location":  {
"uri":  "roslyn\\src\\InteractiveWindow\\EditorTest\\InteractiveWindowTests.cs",
"region":  {
"startLine":  186,
"startColumn":  37,
"endLine":  186,
"endColumn":  42
}
}
},
{
"id":  "S2971",
"message":  "Drop \"Where\" and move the condition into the \"SingleOrDefault\".",
"location":  {
"uri":  "roslyn\\src\\InteractiveWindow\\EditorTest\\InteractiveWindowTests.cs",
"region":  {
"startLine":  187,
"startColumn":  37,
"endLine":  187,
"endColumn":  42
}
}
}
]
}
