{
"issues":  [
{
"id":  "S3237",
"message":  "Use the \"value\" parameter in this event accessor declaration.",
"location":  {
"uri":  "roslyn\\src\\Compilers\\Core\\Portable\\Text\\SourceText.cs",
"region":  {
"startLine":  1069,
"startColumn":  17,
"endLine":  1069,
"endColumn":  20
}
}
},
{
"id":  "S3237",
"message":  "Use the \"value\" parameter in this event accessor declaration.",
"location":  {
"uri":  "roslyn\\src\\Compilers\\Core\\Portable\\Text\\SourceText.cs",
"region":  {
"startLine":  1074,
"startColumn":  17,
"endLine":  1074,
"endColumn":  23
}
}
}
]
}
