{
"issues":  [
{
"id":  "S2583",
"message":  "Change this condition so that it does not always evaluate to \"true\".",
"location":  {
"uri":  "roslyn\\src\\EditorFeatures\\Core\\Implementation\\InlineRename\\AbstractEditorInlineRenameService.cs",
"region":  {
"startLine":  121,
"startColumn":  17,
"endLine":  121,
"endColumn":  31
}
}
},
{
"id":  "S2583",
"message":  "Change this condition so that it does not always evaluate to \"true\".",
"location":  {
"uri":  "roslyn\\src\\EditorFeatures\\Core\\Implementation\\ReferenceHighlighting\\ReferenceHighlightingViewTaggerProvider.cs",
"region":  {
"startLine":  131,
"startColumn":  21,
"endLine":  131,
"endColumn":  37
}
}
}
]
}
