{
"issues":  [
{
"id":  "S1172",
"message":  "Remove this unused method parameter \"module\".",
"location":  {
"uri":  "roslyn\\src\\ExpressionEvaluator\\CSharp\\Source\\ExpressionCompiler\\CompilationContext.cs",
"region":  {
"startLine":  869,
"startColumn":  76,
"endLine":  869,
"endColumn":  97
}
}
},
{
"id":  "S1172",
"message":  "Remove this unused method parameter \"container\".",
"location":  {
"uri":  "roslyn\\src\\ExpressionEvaluator\\CSharp\\Source\\ExpressionCompiler\\Symbols\\ObjectIdLocalSymbol.cs",
"region":  {
"startLine":  35,
"startColumn":  92,
"endLine":  35,
"endColumn":  119
}
}
}
]
}
