{
"issues":  [
{
"id":  "S2259",
"message":  "\"symbolDeclaredEvent\" is null on at least one execution path.",
"location":  {
"uri":  "roslyn\\src\\Compilers\\Core\\Portable\\DiagnosticAnalyzer\\AnalysisState.cs",
"region":  {
"startLine":  254,
"startColumn":  83,
"endLine":  254,
"endColumn":  102
}
}
},
{
"id":  "S2259",
"message":  "\"b\" is null on at least one execution path.",
"location":  {
"uri":  "roslyn\\src\\Compilers\\Core\\Portable\\InternalUtilities\\JsonWriter.cs",
"region":  {
"startLine":  202,
"startColumn":  25,
"endLine":  202,
"endColumn":  26
}
}
},
{
"id":  "S2259",
"message":  "\"b\" is null on at least one execution path.",
"location":  {
"uri":  "roslyn\\src\\Compilers\\Core\\Portable\\InternalUtilities\\JsonWriter.cs",
"region":  {
"startLine":  205,
"startColumn":  25,
"endLine":  205,
"endColumn":  26
}
}
},
{
"id":  "S2259",
"message":  "\"typesInLastChildNamespace\" is null on at least one execution path.",
"location":  {
"uri":  "roslyn\\src\\Compilers\\Core\\Portable\\MetadataReader\\MetadataHelpers.cs",
"region":  {
"startLine":  761,
"startColumn":  29,
"endLine":  761,
"endColumn":  54
}
}
},
{
"id":  "S2259",
"message":  "\"nameDirectory\" is null on at least one execution path.",
"location":  {
"uri":  "roslyn\\src\\Compilers\\Core\\Portable\\PEWriter\\NativeResourceWriter.cs",
"region":  {
"startLine":  212,
"startColumn":  25,
"endLine":  212,
"endColumn":  38
}
}
},
{
"id":  "S2259",
"message":  "\"nameDirectory\" is null on at least one execution path.",
"location":  {
"uri":  "roslyn\\src\\Compilers\\Core\\Portable\\PEWriter\\NativeResourceWriter.cs",
"region":  {
"startLine":  216,
"startColumn":  25,
"endLine":  216,
"endColumn":  38
}
}
},
{
"id":  "S2259",
"message":  "\"languageDirectory\" is null on at least one execution path.",
"location":  {
"uri":  "roslyn\\src\\Compilers\\Core\\Portable\\PEWriter\\NativeResourceWriter.cs",
"region":  {
"startLine":  223,
"startColumn":  17,
"endLine":  223,
"endColumn":  34
}
}
},
{
"id":  "S2259",
"message":  "\"pointer\" is null on at least one execution path.",
"location":  {
"uri":  "roslyn\\src\\Compilers\\Core\\Portable\\PEWriter\\TypeNameSerializer.cs",
"region":  {
"startLine":  182,
"startColumn":  56,
"endLine":  182,
"endColumn":  63
}
}
},
{
"id":  "S2259",
"message":  "\"oldPrefix\" is null on at least one execution path.",
"location":  {
"uri":  "roslyn\\src\\Compilers\\Core\\Portable\\SourceFileResolver.cs",
"region":  {
"startLine":  97,
"startColumn":  111,
"endLine":  97,
"endColumn":  120
}
}
},
{
"id":  "S2259",
"message":  "\"annotations\" is null on at least one execution path.",
"location":  {
"uri":  "roslyn\\src\\Compilers\\Core\\Portable\\Syntax\\GreenNode.cs",
"region":  {
"startLine":  77,
"startColumn":  44,
"endLine":  77,
"endColumn":  55
}
}
},
{
"id":  "S2259",
"message":  "\"annotations\" is null on at least one execution path.",
"location":  {
"uri":  "roslyn\\src\\Compilers\\Core\\Portable\\Syntax\\GreenNode.cs",
"region":  {
"startLine":  92,
"startColumn":  44,
"endLine":  92,
"endColumn":  55
}
}
},
{
"id":  "S2259",
"message":  "\"node\" is null on at least one execution path.",
"location":  {
"uri":  "roslyn\\src\\Compilers\\Core\\Portable\\Syntax\\GreenNode.cs",
"region":  {
"startLine":  763,
"startColumn":  37,
"endLine":  763,
"endColumn":  41
}
}
},
{
"id":  "S2259",
"message":  "\"node\" is null on at least one execution path.",
"location":  {
"uri":  "roslyn\\src\\Compilers\\Core\\Portable\\Syntax\\GreenNode.cs",
"region":  {
"startLine":  785,
"startColumn":  30,
"endLine":  785,
"endColumn":  34
}
}
},
{
"id":  "S2259",
"message":  "\"node\" is null on at least one execution path.",
"location":  {
"uri":  "roslyn\\src\\Compilers\\Core\\Portable\\Syntax\\GreenNode.cs",
"region":  {
"startLine":  807,
"startColumn":  30,
"endLine":  807,
"endColumn":  34
}
}
}
]
}
