{
"issues":  [
{
"id":  "S105",
"message":  "Replace all tab characters in this file by sequences of white-spaces.",
"location":  {
"uri":  "roslyn\\src\\VisualStudio\\Core\\Test\\Snippets\\CSharpSnippetExpansionClientTests.vb",
"region":  {
"startLine":  255,
"startColumn":  1,
"endLine":  255,
"endColumn":  1
}
}
},
{
"id":  "S105",
"message":  "Replace all tab characters in this file by sequences of white-spaces.",
"location":  {
"uri":  "roslyn\\src\\VisualStudio\\Core\\Test\\Snippets\\VisualBasicSnippetExpansionClientTests.vb",
"region":  {
"startLine":  338,
"startColumn":  1,
"endLine":  338,
"endColumn":  1
}
}
},
{
"id":  "S105",
"message":  "Replace all tab characters in this file by sequences of white-spaces.",
"location":  {
"uri":  "roslyn\\src\\VisualStudio\\Core\\Test\\Venus\\VisualBasicContainedLanguageSupportTests.vb",
"region":  {
"startLine":  190,
"startColumn":  1,
"endLine":  190,
"endColumn":  1
}
}
}
]
}
