{
"issues":  [
{
"id":  "S100",
"message":  "Rename method \"ExtraMSCorLibCS\" to match camel case naming rules, consider using \"ExtraMsCorLibCS\".",
"location":  {
"uri":  "roslyn\\src\\Compilers\\Server\\VBCSCompilerTests\\CompilerServerTests.cs",
"region":  {
"startLine":  410,
"startColumn":  27,
"endLine":  410,
"endColumn":  42
}
}
},
{
"id":  "S100",
"message":  "Rename method \"ExtraMSCorLibVB\" to match camel case naming rules, consider using \"ExtraMsCorLibVB\".",
"location":  {
"uri":  "roslyn\\src\\Compilers\\Server\\VBCSCompilerTests\\CompilerServerTests.cs",
"region":  {
"startLine":  440,
"startColumn":  27,
"endLine":  440,
"endColumn":  42
}
}
}
]
}
